rocketchat_py_sdk/__init__.py
rocketchat_py_sdk/driver.py
rocketchat_py_sdk-0.0.8.dist-info/METADATA
rocketchat_py_sdk-0.0.8.dist-info/RECORD
rocketchat_py_sdk-0.0.8.dist-info/WHEEL
rocketchat_py_sdk-0.0.8.dist-info/top_level.txt
