Metadata-Version: 2.1
Name: rocketchat-py-sdk
Version: 0.0.8
Summary: A easy way to connect and interact with Rocket.Chat
Home-page: https://github.com/RocketChat/Rocket.Chat.py.SDK
Author: Arthur Temporim
Author-email: arthurrtl@gmail.com
License: UNKNOWN
Keywords: python,Rocket.Chat,driver
Platform: UNKNOWN
Classifier: Programming Language :: Python :: 3
Classifier: License :: OSI Approved :: MIT License
Classifier: Operating System :: OS Independent
Requires-Dist: DateTime (==4.2)
Requires-Dist: python-ddp (==0.1.5)
Requires-Dist: pyee (==5.0.0)
